maagnar/__init__.py
maagnar/entry_point.py
maagnar/lib.py
maagnar-1.0.2.dist-info/LICENSE
maagnar-1.0.2.dist-info/METADATA
maagnar-1.0.2.dist-info/WHEEL
maagnar-1.0.2.dist-info/entry_points.txt
maagnar-1.0.2.dist-info/top_level.txt
maagnar-1.0.2.dist-info/RECORD
