Metadata-Version: 2.1
Name: maagnar
Version: 1.0.2
Summary: Library and command line entry point for generating anagrams
Home-page: https://github.com/induane/maagnar
Author: Brant Watson
Author-email: oldspiceap@gmail.com
License: MIT License
Platform: UNKNOWN
Requires-Dist: log-color
Requires-Dist: diskcache
